Metadata-Version: 1.0
Name: shakhov-package
Version: 0.1.0
Summary: Shakhov package
Home-page: https://github.com/
Author: Ilya Shakhov
Author-email: 284560@niuitmo.ru
License: UNKNOWN
Platform: UNKNOWN
